setup.py
proba_distribtuion/Binomialdistribution.py
proba_distribtuion/Gaussiandistribution.py
proba_distribtuion/Generaldistribution.py
proba_distribtuion/__init__.py
proba_distribtuion.egg-info/PKG-INFO
proba_distribtuion.egg-info/SOURCES.txt
proba_distribtuion.egg-info/dependency_links.txt
proba_distribtuion.egg-info/not-zip-safe
proba_distribtuion.egg-info/top_level.txt