Metadata-Version: 1.0
Name: proba-distribtuion
Version: 0.1
Summary: A simple package for Gaussian and Binomial Distributions
Home-page: UNKNOWN
Author: UNKNOWN
Author-email: UNKNOWN
License: UNKNOWN
Platform: UNKNOWN
